silhouette_upper_bound/__init__.py
silhouette_upper_bound/utils.py
silhouette_upper_bound-0.1.2.dist-info/METADATA
silhouette_upper_bound-0.1.2.dist-info/WHEEL
silhouette_upper_bound-0.1.2.dist-info/licenses/LICENSE
silhouette_upper_bound-0.1.2.dist-info/RECORD
