Metadata-Version: 2.4
Name: silhouette-upper-bound
Version: 0.1.2
Summary: An upper bound of the Average Silhouette Width
Project-URL: homepage, https://github.com/hugo-strang/silhouette-upper-bound
Author-email: Hugo Sträng <hugo.strang2@gmail.com>
License-Expression: MIT
License-File: LICENSE
Classifier: Programming Language :: Python :: 3
Requires-Python: >=3.9
Requires-Dist: numba>=0.61.2
Requires-Dist: numpy>=1.22.0
Provides-Extra: dev
Requires-Dist: black; extra == 'dev'
Provides-Extra: examples
Requires-Dist: matplotlib; extra == 'examples'
Requires-Dist: pandas; extra == 'examples'
Requires-Dist: seaborn; extra == 'examples'
Requires-Dist: tqdm; extra == 'examples'
Provides-Extra: tests
Requires-Dist: kmedoids; extra == 'tests'
Requires-Dist: pytest; extra == 'tests'
Requires-Dist: pytest-cov; extra == 'tests'
Requires-Dist: scikit-learn; extra == 'tests'
